{
  "type": "daily_comfort",
  "theme": "자신을 사랑하는 방법",
  "title": "오늘의 위로: 자신을 사랑하는 방법",
  "date": "2025년 09월 06일",
  "duration": "3분",
  "content": "완벽하지 않아도 괜찮아요. \n\n당신은 그 자체로 소중합니다. \n\n자신의 감정을 인정해주세요. \n\n슬플 때는 슬퍼도 됩니다. \n\n화날 때는 화내도 됩니다. \n\n그 모든 감정이 당신의 일부예요. \n\n자신을 용서해주세요. \n\n실수해도 괜찮습니다. \n\n당신은 이미 충분히 사랑받을 만한 사람입니다. \n\n오늘부터 자신을 더 사랑해주세요.",
  "structure": {
    "intro": "10-15초 - 채널 로고 + '오늘의 위로' 타이틀 + 주제 소개",
    "main_message": "120-130초 - 이어지는 위로 글귀 낭독 (6-8개 단락)",
    "outro": "20-30초 - 요약 + '당신은 혼자가 아닙니다' + 다음 영상 안내"
  },
  "timing": {
    "0:00-0:15": "인트로 - 로고 + 제목 카드 + 주제 소개",
    "0:15-2:25": "본문 위로글 - 6-8개 단락으로 이어지는 글귀 낭독",
    "2:25-3:00": "아웃로 - 요약 + 구독/다음 영상 안내"
  },
  "visual_elements": [
    "부드러운 구름",
    "평화로운 호수",
    "따뜻한 파스텔 톤"
  ],
  "audio_elements": [
    "감성적인 피아노",
    "따뜻하고 부드러운 내레이션"
  ],
  "tags": [
    "위로",
    "힐링",
    "일상위로",
    "maro",
    "마음위로",
    "자존감",
    "자기계발",
    "루틴"
  ],
  "production_notes": {
    "bgm_suggestion": "따뜻하고 잔잔한 피아노/스트링 중심",
    "narration_tone": "따뜻하고 공감되는 톤, 문장 끝마다 1-2초 멈춤",
    "visual_style": "자연스럽고 따뜻한 파스텔 톤, 부드러운 전환",
    "subtitle_font": "둥근고딕 또는 산세리프 계열, 가독성 중심"
  }
}